odoo/addons/product_configurator_mrp_component/README.rst
odoo/addons/product_configurator_mrp_component/__init__.py
odoo/addons/product_configurator_mrp_component/__manifest__.py
odoo/addons/product_configurator_mrp_component/i18n/product_configurator_mrp_component.pot
odoo/addons/product_configurator_mrp_component/models/__init__.py
odoo/addons/product_configurator_mrp_component/models/mrp_bom.py
odoo/addons/product_configurator_mrp_component/models/mrp_bom_line_config.py
odoo/addons/product_configurator_mrp_component/models/product_config.py
odoo/addons/product_configurator_mrp_component/readme/CONFIGURE.rst
odoo/addons/product_configurator_mrp_component/readme/DESCRIPTION.rst
odoo/addons/product_configurator_mrp_component/readme/USAGE.rst
odoo/addons/product_configurator_mrp_component/security/ir.model.access.csv
odoo/addons/product_configurator_mrp_component/static/description/icon.png
odoo/addons/product_configurator_mrp_component/static/description/index.html
odoo/addons/product_configurator_mrp_component/views/mrp_bom.xml
odoo14_addon_product_configurator_mrp_component-14.0.1.1.3.dist-info/METADATA
odoo14_addon_product_configurator_mrp_component-14.0.1.1.3.dist-info/WHEEL
odoo14_addon_product_configurator_mrp_component-14.0.1.1.3.dist-info/top_level.txt
odoo14_addon_product_configurator_mrp_component-14.0.1.1.3.dist-info/RECORD
